pes_sipo/pes_sipo_net.v
/* Generated by Yosys 0.32+74 (git sha1 b739213d9, gcc 12.3.0-1ubuntu1~22.04 -fPIC -Os) */

module d_ff(clk, d, rst, q);
  input clk;
  wire clk;
  input d;
  wire d;
  output q;
  reg q;
  input rst;
  wire rst;
  always @(posedge clk)
    if (rst) q <= 1'h0;
    else q <= d;
endmodule

module pes_sipo(clk, b, q);
  input b;
  wire b;
  input clk;
  wire clk;
  output [3:0] q;
  wire [3:0] q;
  d_ff dut1 (
    .clk(clk),
    .d(b),
    .q(q[3])
  );
  d_ff dut2 (
    .clk(clk),
    .d(q[3]),
    .q(q[2])
  );
  d_ff dut3 (
    .clk(clk),
    .d(q[2]),
    .q(q[1])
  );
  d_ff dut4 (
    .clk(clk),
    .d(q[1]),
    .q(q[0])
  );
endmodule

pes_sipo/pes_sipo_tb.v
module sipo_tb();

reg clk,b;
wire [3:0]q;

pes_sipo uut(.clk(clk),.b(b),.q(q));

initial
begin
$dumpfile ("sipo.vcd");
 $dumpvars (0,sipo_tb);
clk=1'b0;
forever #5clk=~clk;
end

initial
begin
$monitor("clk=%d,b=%d,q=%d",clk,b,q);
end

initial
begin
b=1;
#10;
b=0;
#10;
b=1;
#10;
b=0;

#50;
$finish;

end

endmodule

pes_sipo/sipo.vcd
$date
	Fri Oct 20 15:39:51 2023
$end
$version
	Icarus Verilog
$end
$timescale
	1ps
$end
$scope module sipo_tb $end
$var wire 4 ! q [3:0] $end
$var reg 1 " b $end
$var reg 1 # clk $end
$scope module uut $end
$var wire 1 " b $end
$var wire 1 # clk $end
$var wire 4 $ q [3:0] $end
$scope module dut1 $end
$var wire 1 # clk $end
$var wire 1 " d $end
$var wire 1 % rst $end
$var reg 1 & q $end
$upscope $end
$scope module dut2 $end
$var wire 1 # clk $end
$var wire 1 ' d $end
$var wire 1 ( rst $end
$var reg 1 ) q $end
$upscope $end
$scope module dut3 $end
$var wire 1 # clk $end
$var wire 1 * d $end
$var wire 1 + rst $end
$var reg 1 , q $end
$upscope $end
$scope module dut4 $end
$var wire 1 # clk $end
$var wire 1 - d $end
$var wire 1 . rst $end
$var reg 1 / q $end
$upscope $end
$upscope $end
$upscope $end
$enddefinitions $end
#0
$dumpvars
x/
z.
x-
x,
z+
x*
x)
z(
x'
x&
z%
bx $
0#
1"
bx !
$end
#5000
1'
b1xxx !
b1xxx $
1&
1#
#10000
0#
0"
#15000
1*
0'
1)
b1xx !
b1xx $
0&
1#
#20000
0#
1"
#25000
1'
0*
1-
1&
0)
b101x !
b101x $
1,
1#
#30000
0#
0"
#35000
0-
1*
0'
1/
0,
1)
b101 !
b101 $
0&
1#
#40000
0#
#45000
0*
1-
0)
1,
b10 !
b10 $
0/
1#
#50000
0#
#55000
0-
1/
b1 !
b1 $
0,
1#
#60000
0#
#65000
b0 !
b0 $
0/
1#
